distroscraper/__init__.py
distroscraper/lib.py
distroscraper/tm_add_torrent.py
distroscraper/tm_get_stats.py
distroscraper/tmlib.py
distroscraper/scrape/__init__.py
distroscraper/scrape/archlinux.py
distroscraper/scrape/centos.py
distroscraper/scrape/debian.py
distroscraper/scrape/fedora.py
distroscraper/scrape/linuxmint.py
distroscraper/scrape/raspberrypi.py
distroscraper-1.0.2.dist-info/LICENSE
distroscraper-1.0.2.dist-info/METADATA
distroscraper-1.0.2.dist-info/WHEEL
distroscraper-1.0.2.dist-info/top_level.txt
distroscraper-1.0.2.dist-info/RECORD
