Metadata-Version: 2.1
Name: distroscraper
Version: 1.0.2
Summary: Scrape Linux Distro torrents and add to Transmission automatically
Home-page: https://jefftickle.com/projects/distroscraper
Author: Jeff Tickle
Author-email: jeff.tickle+pypi@protonmail.com
License: UNKNOWN
Platform: UNKNOWN
Classifier: Development Status :: 5 - Production/Stable
Classifier: Environment :: Console
Classifier: License :: OSI Approved :: GNU General Public License v3 or later (GPLv3+)
Classifier: Natural Language :: English
Classifier: Operating System :: OS Independent
Classifier: Topic :: Communications :: File Sharing
Classifier: Topic :: Internet :: WWW/HTTP
Classifier: Topic :: System :: Installation/Setup
Classifier: Topic :: System :: Operating System
Classifier: Topic :: System :: Software Distribution
Classifier: Topic :: Utilities
Requires-Python: >=3.6
Requires-Dist: beautifulsoup4
Requires-Dist: lxml
Requires-Dist: requests
Requires-Dist: transmissionrpc
Requires-Dist: htmlmin
